pytrydan/__init__.py
pytrydan/__main__.py
pytrydan/cli.py
pytrydan/const.py
pytrydan/exceptions.py
pytrydan/main.py
pytrydan/models/trydan.py
pytrydan/py.typed
pytrydan/trydan.py
pytrydan-0.8.1.dist-info/LICENSE
pytrydan-0.8.1.dist-info/METADATA
pytrydan-0.8.1.dist-info/WHEEL
pytrydan-0.8.1.dist-info/entry_points.txt
pytrydan-0.8.1.dist-info/RECORD
