Metadata-Version: 2.1
Name: pytrydan
Version: 0.8.1
Summary: Library to interface with V2C EVSE Trydan
Home-page: https://github.com/dgomes/pytrydan
License: MIT
Author: Diogo Gomes
Author-email: diogogomes@gmail.com
Requires-Python: >=3.10,<4.0
Classifier: Development Status :: 2 - Pre-Alpha
Classifier: Intended Audience :: Developers
Classifier: License :: OSI Approved :: MIT License
Classifier: Natural Language :: English
Classifier: Operating System :: OS Independent
Classifier: Programming Language :: Python :: 3
Classifier: Programming Language :: Python :: 3.10
Classifier: Programming Language :: Python :: 3.11
Classifier: Programming Language :: Python :: 3.12
Classifier: Topic :: Software Development :: Libraries
Requires-Dist: httpx (>=0.24.0)
Requires-Dist: orjson (>=3.9.2)
Requires-Dist: rich (>=10)
Requires-Dist: tenacity (>=8.2.2,<9.0.0)
Requires-Dist: typer (>=0.7.0)
Project-URL: Bug Tracker, https://github.com/dgomes/pytrydan/issues
Project-URL: Changelog, https://github.com/dgomes/pytrydan/blob/main/CHANGELOG.md
Project-URL: Documentation, https://pytrydan.readthedocs.io
Project-URL: Repository, https://github.com/dgomes/pytrydan
